bits.py
binary_bits-1.1.0.dist-info/LICENSE
binary_bits-1.1.0.dist-info/METADATA
binary_bits-1.1.0.dist-info/WHEEL
binary_bits-1.1.0.dist-info/top_level.txt
binary_bits-1.1.0.dist-info/RECORD
