Metadata-Version: 2.1
Name: binary-bits
Version: 1.1.0
Summary: Provide additional methods for working with binary data
Home-page: https://github.com/wolfpackmars2/bits
Author: S Groesz
License: UNKNOWN
Project-URL: Source, http://git.groesz.org/wp/bits/
Platform: UNKNOWN
Classifier: Development Status :: 5 - Production/Stable
Classifier: Intended Audience :: Developers
Classifier: Topic :: Software Development :: Libraries :: Python Modules
Classifier: Programming Language :: Python :: 3
Classifier: Programming Language :: Python :: Implementation :: CPython
Classifier: License :: OSI Approved :: MIT License
Classifier: Operating System :: OS Independent
Requires-Python: >=3.6
Provides-Extra: test
Requires-Dist: coverage ; extra == 'test'
